[
  {
    "word": "mother",
    "value": 7
  },
  {
    "word": "boy",
    "value": 7
  },
  {
    "word": "woman",
    "value": 6
  },
  {
    "word": "water",
    "value": 5
  },
  {
    "word": "voice",
    "value": 5
  },
  {
    "word": "river",
    "value": 4
  },
  {
    "word": "sword",
    "value": 4
  },
  {
    "word": "crowd",
    "value": 4
  },
  {
    "word": "mud",
    "value": 3
  },
  {
    "word": "catfish",
    "value": 3
  },
  {
    "word": "garbage",
    "value": 3
  },
  {
    "word": "thing",
    "value": 3
  },
  {
    "word": "fump",
    "value": 3
  },
  {
    "word": "police",
    "value": 3
  },
  {
    "word": "news",
    "value": 3
  },
  {
    "word": "reporter",
    "value": 3
  },
  {
    "word": "way",
    "value": 2
  },
  {
    "word": "face",
    "value": 2
  },
  {
    "word": "thought",
    "value": 2
  },
  {
    "word": "vision",
    "value": 2
  },
  {
    "word": "foot",
    "value": 2
  },
  {
    "word": "gloom",
    "value": 2
  },
  {
    "word": "silt",
    "value": 2
  },
  {
    "word": "fire",
    "value": 2
  },
  {
    "word": "wrapper",
    "value": 2
  },
  {
    "word": "problem",
    "value": 2
  },
  {
    "word": "surface",
    "value": 2
  },
  {
    "word": "color",
    "value": 2
  },
  {
    "word": "time",
    "value": 2
  },
  {
    "word": "head",
    "value": 2
  },
  {
    "word": "word",
    "value": 2
  },
  {
    "word": "throat",
    "value": 2
  },
  {
    "word": "father",
    "value": 2
  },
  {
    "word": "hole",
    "value": 2
  },
  {
    "word": "lady",
    "value": 2
  },
  {
    "word": "camera",
    "value": 2
  },
  {
    "word": "explosion",
    "value": 2
  },
  {
    "word": "revelation",
    "value": 1
  },
  {
    "word": "term",
    "value": 1
  },
  {
    "word": "mortality",
    "value": 1
  },
  {
    "word": "death",
    "value": 1
  },
  {
    "word": "et",
    "value": 1
  },
  {
    "word": "cetera",
    "value": 1
  },
  {
    "word": "truth",
    "value": 1
  },
  {
    "word": "speed",
    "value": 1
  },
  {
    "word": "truck",
    "value": 1
  },
  {
    "word": "wind",
    "value": 1
  },
  {
    "word": "lung",
    "value": 1
  },
  {
    "word": "steeple",
    "value": 1
  },
  {
    "word": "skyscraper",
    "value": 1
  }
]